{
  "Header": {
    "title": "We are a Landing Page",
    "paragraph": "Lorem ipsum dolor sit amet, consectetur adipiscing elit. Duis sed dapibus leo nec ornare diam sed commodo nibh ante facilisis bibendum."
  },
  "About": {
    "paragraph": "Lorem ipsum dolor sit amet, consectetur adipiscing elit, sed do eiusmod tempor incididunt ut labore et dolore magna aliqua. Ut enim ad minim veniam, quis nostrud exercitation ullamco laboris nisi ut aliquip ex ea commodo consequat. Lorem ipsum dolor sit amet, consectetur adipiscing elit, sed do eiusmod tempor incididunt ut labore et dolore magna aliqua.",
    "Why": [
      "Lorem ipsum dolor",
      "Tempor incididunt",
      "Lorem ipsum dolor",
      "Incididunt ut labore"
    ],
    "Why2": [
      "Aliquip ex ea commodo",
      "Lorem ipsum dolor",
      "Exercitation ullamco",
      "Lorem ipsum dolor"
    ]
  },
  "Gallery": [
    {
      "title": "Архангай",
      "smallImage": "img/portfolio/01-small.jpg",
      "url": "https://www.facebook.com/arkhangaihan"
    },
    
    {
      "title": "Баян-Өлгий",
      "smallImage": "img/portfolio/02-small.svg",
      "url": "https://www.facebook.com/arkhangaihan"
    },
    {
      "title": "Баянхонгор",
     
      "smallImage": "img/portfolio/03-small.jpg"
    },
    {
      "title": "Булган",
      
      "smallImage": "img/portfolio/04-small.svg"
    },
    {
      "title": "Говь-Алтай",
      
      "smallImage": "img/portfolio/05-small.svg"
    },
    {
      "title": "Говьсүмбэр",
      
      "smallImage": "img/portfolio/06-small.svg"
    },
    {
      "title": "Дархан-Уул",
      
      "smallImage": "img/portfolio/07-small.svg"
    },
    {
      "title": "Дорноговь",
      
      "smallImage": "img/portfolio/08-small.svg"
    },
    {
      "title": "Дорнод",
      
      "smallImage": "img/portfolio/09-small.svg"
    },
    {
      "title": "Дундговь",
      
      "smallImage": "img/portfolio/10-small.svg"
    },
    {
      "title": "Завхан",
      
      "smallImage": "img/portfolio/11-small.svg"
    },
    {
      "title": "Орхон",
      
      "smallImage": "img/portfolio/12-small.png"
    },
    {
      "title": "Өвөрхангай",
      
      "smallImage": "img/portfolio/13-small.svg"
    },
    {
      "title": "Өмнөговь",
      
      "smallImage": "img/portfolio/14-small.svg"
    },
    {
      "title": "Сүхбаатар",
      
      "smallImage": "img/portfolio/15-small.svg"
    },
    {
      "title": "Сэлэнгэ",
      
      "smallImage": "img/portfolio/16-small.svg"
    },
    {
      "title": "Төв",
      
      "smallImage": "img/portfolio/17-small.svg"
    },
    {
      "title": "Увс",
      
      "smallImage": "img/portfolio/18-small.svg"
    },
    {
      "title": "Ховд",
      
      "smallImage": "img/portfolio/19-small.svg"
    },
    {
      "title": "Хөвсгөл",
      
      "smallImage": "img/portfolio/20-small.svg"
    },
    {
      "title": "Хэнтий",
      
      "smallImage": "img/portfolio/21-small.svg"
    }
  ],
  "Services": [
    {
      "icon": "fa fa-wordpress",
      "name": "Lorem ipsum dolor",
      "text": "Lorem ipsum dolor sit amet, consectetur adipiscing elit. Duis sed dapibus leo nec ornare diam sedasd commodo nibh ante facilisis bibendum dolor feugiat at."
    },
    {
      "icon": "fa fa-cart-arrow-down",
      "name": "Consectetur adipiscing",
      "text": "Lorem ipsum dolor sit amet, consectetur adipiscing elit. Duis sed dapibus leo nec ornare diam sedasd commodo nibh ante facilisis bibendum dolor feugiat at."
    },
    {
      "icon": "fa fa-cloud-download",
      "name": "Lorem ipsum dolor",
      "text": "Lorem ipsum dolor sit amet, consectetur adipiscing elit. Duis sed dapibus leo nec ornare diam sedasd commodo nibh ante facilisis bibendum dolor feugiat at."
    },
    {
      "icon": "fa fa-language",
      "name": "Consectetur adipiscing",
      "text": "Lorem ipsum dolor sit amet, consectetur adipiscing elit. Duis sed dapibus leo nec ornare diam sedasd commodo nibh ante facilisis bibendum dolor feugiat at."
    },
    {
      "icon": "fa fa-plane",
      "name": "Lorem ipsum dolor",
      "text": "Lorem ipsum dolor sit amet, consectetur adipiscing elit. Duis sed dapibus leo nec ornare diam sedasd commodo nibh ante facilisis bibendum dolor feugiat at."
    },
    {
      "icon": "fa fa-pie-chart",
      "name": "Consectetur adipiscing",
      "text": "Lorem ipsum dolor sit amet, consectetur adipiscing elit. Duis sed dapibus leo nec ornare diam sedasd commodo nibh ante facilisis bibendum dolor feugiat at."
    }
  ],
  "Testimonials": [
    {
      "img": "img/testimonials/01.jpg",
      "text": "\"Lorem ipsum dolor sit amet, consectetur adipiscing elit. Duis sed dapibus leo nec ornare diam sedasd commodo nibh ante facilisis bibendum dolor feugiat at.\"",
      "name": "John Doe"
    },
    {
      "img": "img/testimonials/02.jpg",
      "text": "\"Lorem ipsum dolor sit amet, consectetur adipiscing elit. Duis sed dapibus leo nec ornare diam sedasd commodo nibh ante facilisis bibendum dolor feugiat at.\"",
      "name": "Johnathan Doe"
    },
    {
      "img": "img/testimonials/03.jpg",
      "text": "\"Lorem ipsum dolor sit amet, consectetur adipiscing elit. Duis sed dapibus leo nec ornare diam sedasd commodo nibh ante facilisis bibendum dolor feugiat at.\"",
      "name": "John Doe"
    },
    {
      "img": "img/testimonials/04.jpg",
      "text": "\"Lorem ipsum dolor sit amet, consectetur adipiscing elit. Duis sed dapibus leo nec ornare diam sedasd commodo nibh ante facilisis bibendum dolor feugiat at.\"",
      "name": "Johnathan Doe"
    },
    {
      "img": "img/testimonials/05.jpg",
      "text": "\"Lorem ipsum dolor sit amet, consectetur adipiscing elit. Duis sed dapibus leo nec ornare diam sedasd commodo nibh ante facilisis bibendum dolor feugiat at.\"",
      "name": "John Doe"
    },
    {
      "img": "img/testimonials/06.jpg",
      "text": "\"Lorem ipsum dolor sit amet, consectetur adipiscing elit. Duis sed dapibus leo nec ornare diam sedasd commodo nibh ante facilisis bibendum dolor feugiat at.\"",
      "name": "Johnathan Doe"
    }
  ],
  "Team": [
    {
      "img": "img/team/01.jpg",
      "name": "John Doe",
      "job": "Director"
    },
    {
      "img": "img/team/02.jpg",
      "name": "Mike Doe",
      "job": "Senior Designer"
    },
    {
      "img": "img/team/03.jpg",
      "name": "Jane Doe",
      "job": "Senior Designer"
    },
    {
      "img": "img/team/04.jpg",
      "name": "Karen Doe",
      "job": "Project Manager"
    }
  ],
  "Contact": {
    "address": "Тусгаар Тогтнолын Ордон 8 давхар, Ulaanbaatar, Mongolia",
    "phone": "+976 91997022",
    "email": "sdwomen4@gmail.com",
    "facebook": "fb.com",
    "twitter": "twitter.com",
    "youtube": "youtube.com"
  },
  "Features": [
    {
      "icon": "fa fa-comments-o",
      "title": "Lorem ipsum",
      "text": "Lorem ipsum dolor sit amet placerat facilisis felis mi in tempus eleifend pellentesque natoque etiam."
    },
    {
      "icon": "fa fa-bullhorn",
      "title": "Lorem ipsum",
      "text": "Lorem ipsum dolor sit amet placerat facilisis felis mi in tempus eleifend pellentesque natoque etiam."
    },
    {
      "icon": "fa fa-group",
      "title": "Lorem ipsum",
      "text": "Lorem ipsum dolor sit amet placerat facilisis felis mi in tempus eleifend pellentesque natoque etiam."
    },
    {
      "icon": "fa fa-magic",
      "title": "Lorem ipsum",
      "text": "Lorem ipsum dolor sit amet placerat facilisis felis mi in tempus eleifend pellentesque natoque etiam."
    }
  ]
}
